dogcat_classifier/__init__.py
dogcat_classifier/classifier.py
dogcat_classifier/model.h5
dogcat_classifier-0.6.dist-info/METADATA
dogcat_classifier-0.6.dist-info/WHEEL
dogcat_classifier-0.6.dist-info/top_level.txt
dogcat_classifier-0.6.dist-info/RECORD
